setup.py
test_vipman_model.egg-info/PKG-INFO
test_vipman_model.egg-info/SOURCES.txt
test_vipman_model.egg-info/dependency_links.txt
test_vipman_model.egg-info/top_level.txt
transform/Transform_txt_xml.py
transform/__init__.py