Metadata-Version: 1.0
Name: test-vipman-model
Version: 0.0.1
Summary: just a simple test of vipkid
Home-page: UNKNOWN
Author: mingrun
Author-email: 13271929138@163.com
License: MIT
Keywords: simple,test
Platform: any
